freshbook/__init__.py
freshbook/cli.py
freshbook/freshbook.py
freshbook/utils.py
freshbook-0.1.5.dist-info/DESCRIPTION.rst
freshbook-0.1.5.dist-info/METADATA
freshbook-0.1.5.dist-info/RECORD
freshbook-0.1.5.dist-info/WHEEL
freshbook-0.1.5.dist-info/entry_points.txt
freshbook-0.1.5.dist-info/metadata.json
freshbook-0.1.5.dist-info/top_level.txt
