Metadata-Version: 2.0
Name: freshbook
Version: 0.1.5
Summary: Freshbooks hours logger tool
Home-page: https://github.com/redraw/freshbook
Author: redraw
Author-email: agustinbv@gmail.com
License: MIT license
Keywords: freshbook
Platform: UNKNOWN
Classifier: Development Status :: 2 - Pre-Alpha
Classifier: Intended Audience :: Developers
Classifier: License :: OSI Approved :: MIT License
Classifier: Natural Language :: English
Classifier: Programming Language :: Python :: 2
Classifier: Programming Language :: Python :: 2.6
Classifier: Programming Language :: Python :: 2.7
Classifier: Programming Language :: Python :: 3
Classifier: Programming Language :: Python :: 3.3
Classifier: Programming Language :: Python :: 3.4
Classifier: Programming Language :: Python :: 3.5
Requires-Dist: docopt
Requires-Dist: refreshbooks (==2.0)
Requires-Dist: requests
Requires-Dist: six
